collist.py
collist-0.5.dist-info/DESCRIPTION.rst
collist-0.5.dist-info/METADATA
collist-0.5.dist-info/RECORD
collist-0.5.dist-info/WHEEL
collist-0.5.dist-info/entry_points.txt
collist-0.5.dist-info/metadata.json
collist-0.5.dist-info/top_level.txt
