Metadata-Version: 2.0
Name: collist
Version: 0.5
Summary: UNKNOWN
Home-page: https://github.com/ninjaaron/collist
Author: Aaron Christianson
Author-email: ninjaaron@gmail.com
License: MIT
Platform: UNKNOWN
Requires-Dist: click
